CHANGELOG
LICENSE
MANIFEST.in
README
setup.cfg
setup.py
docs/index.txt
docs/sample.cfg
nosy/__init__.py
nosy/nosy.py
nosy.egg-info/PKG-INFO
nosy.egg-info/SOURCES.txt
nosy.egg-info/dependency_links.txt
nosy.egg-info/entry_points.txt
nosy.egg-info/top_level.txt